{
  "acumulado": false,
  "dataApuracao": "22/02/2006",
  "dataProximoConcurso": "25/02/2006",
  "dezenasSorteadasOrdemSorteio": [
    "29",
    "47",
    "12",
    "50",
    "16",
    "28"
  ],
  "exibirDetalhamentoPorCidade": true,
  "id": null,
  "indicadorConcursoEspecial": 1,
  "listaDezenas": [
    "12",
    "16",
    "28",
    "29",
    "47",
    "50"
  ],
  "listaDezenasSegundoSorteio": null,
  "listaMunicipioUFGanhadores": [
    {
      "ganhadores": 1,
      "municipio": "",
      "nomeFatansiaUL": "",
      "posicao": 1,
      "serie": "",
      "uf": "PR"
    }
  ],
  "listaRateioPremio": [
    {
      "descricaoFaixa": "6 acertos",
      "faixa": 1,
      "numeroDeGanhadores": 1,
      "valorPremio": 26132814.65
    },
    {
      "descricaoFaixa": "5 acertos",
      "faixa": 2,
      "numeroDeGanhadores": 90,
      "valorPremio": 17953.91
    },
    {
      "descricaoFaixa": "4 acertos",
      "faixa": 3,
      "numeroDeGanhadores": 6943,
      "valorPremio": 231.85
    }
  ],
  "listaResultadoEquipeEsportiva": null,
  "localSorteio": "Caminhão da Sorte",
  "nomeMunicipioUFSorteio": "CORUMBÁ, MS",
  "nomeTimeCoracaoMesSorte": "",
  "numero": 740,
  "numeroConcursoAnterior": 739,
  "numeroConcursoFinal_0_5": 745,
  "numeroConcursoProximo": 741,
  "numeroJogo": 2,
  "observacao": "Estimativa de prêmio (sena) para o próximo concurso, a ser realizado em 25/02/2006: R$1.000.000,00.",
  "premiacaoContingencia": null,
  "tipoJogo": "MEGA_SENA",
  "tipoPublicacao": 3,
  "ultimoConcurso": true,
  "valorArrecadado": 0.0,
  "valorAcumuladoConcurso_0_5": 2019814.95,
  "valorAcumuladoConcursoEspecial": 0.0,
  "valorAcumuladoProximoConcurso": 0.0,
  "valorEstimadoProximoConcurso": 0.0,
  "valorSaldoReservaGarantidora": 0.0,
  "valorTotalPremioFaixaUm": 0.0
}