{
  "acumulado": true,
  "dataApuracao": "14/01/2015",
  "dataProximoConcurso": "17/01/2015",
  "dezenasSorteadasOrdemSorteio": [
    "29",
    "28",
    "31",
    "48",
    "45",
    "49"
  ],
  "exibirDetalhamentoPorCidade": true,
  "id": null,
  "indicadorConcursoEspecial": 1,
  "listaDezenas": [
    "28",
    "29",
    "31",
    "45",
    "48",
    "49"
  ],
  "listaDezenasSegundoSorteio": null,
  "listaMunicipioUFGanhadores": [],
  "listaRateioPremio": [
    {
      "descricaoFaixa": "6 acertos",
      "faixa": 1,
      "numeroDeGanhadores": 0,
      "valorPremio": 0.0
    },
    {
      "descricaoFaixa": "5 acertos",
      "faixa": 2,
      "numeroDeGanhadores": 54,
      "valorPremio": 39170.42
    },
    {
      "descricaoFaixa": "4 acertos",
      "faixa": 3,
      "numeroDeGanhadores": 3941,
      "valorPremio": 766.73
    }
  ],
  "listaResultadoEquipeEsportiva": null,
  "localSorteio": "Estúdio de TV",
  "nomeMunicipioUFSorteio": "Osasco, SP",
  "nomeTimeCoracaoMesSorte": "",
  "numero": 1669,
  "numeroConcursoAnterior": 1668,
  "numeroConcursoFinal_0_5": 1670,
  "numeroConcursoProximo": 1670,
  "numeroJogo": 2,
  "observacao": "",
  "premiacaoContingencia": null,
  "tipoJogo": "MEGA_SENA",
  "tipoPublicacao": 3,
  "ultimoConcurso": true,
  "valorArrecadado": 36129242.5,
  "valorAcumuladoConcurso_0_5": 15671923.1,
  "valorAcumuladoConcursoEspecial": 1889008.61,
  "valorAcumuladoProximoConcurso": 15671923.1,
  "valorEstimadoProximoConcurso": 20000000.0,
  "valorSaldoReservaGarantidora": 0.0,
  "valorTotalPremioFaixaUm": 0.0
}