{
  "acumulado": true,
  "dataApuracao": "22/06/2013",
  "dataProximoConcurso": "26/06/2013",
  "dezenasSorteadasOrdemSorteio": [
    "32",
    "01",
    "06",
    "09",
    "16",
    "02"
  ],
  "exibirDetalhamentoPorCidade": true,
  "id": null,
  "indicadorConcursoEspecial": 1,
  "listaDezenas": [
    "01",
    "02",
    "06",
    "09",
    "16",
    "32"
  ],
  "listaDezenasSegundoSorteio": null,
  "listaMunicipioUFGanhadores": [],
  "listaRateioPremio": [
    {
      "descricaoFaixa": "6 acertos",
      "faixa": 1,
      "numeroDeGanhadores": 0,
      "valorPremio": 0.0
    },
    {
      "descricaoFaixa": "5 acertos",
      "faixa": 2,
      "numeroDeGanhadores": 263,
      "valorPremio": 9151.9
    },
    {
      "descricaoFaixa": "4 acertos",
      "faixa": 3,
      "numeroDeGanhadores": 15199,
      "valorPremio": 226.23
    }
  ],
  "listaResultadoEquipeEsportiva": null,
  "localSorteio": "Caminhão da Sorte",
  "nomeMunicipioUFSorteio": "SÃO JOÃO DA BARRA, RJ",
  "nomeTimeCoracaoMesSorte": "",
  "numero": 1505,
  "numeroConcursoAnterior": 1504,
  "numeroConcursoFinal_0_5": 1510,
  "numeroConcursoProximo": 1506,
  "numeroJogo": 2,
  "observacao": "",
  "premiacaoContingencia": null,
  "tipoJogo": "MEGA_SENA",
  "tipoPublicacao": 3,
  "ultimoConcurso": true,
  "valorArrecadado": 41112500.0,
  "valorAcumuladoConcurso_0_5": 2786994.73,
  "valorAcumuladoConcursoEspecial": 28385940.5,
  "valorAcumuladoProximoConcurso": 24873756.07,
  "valorEstimadoProximoConcurso": 29500000.0,
  "valorSaldoReservaGarantidora": 0.0,
  "valorTotalPremioFaixaUm": 0.0
}