{
  "acumulado": false,
  "dataApuracao": "07/07/2007",
  "dataProximoConcurso": "11/07/2007",
  "dezenasSorteadasOrdemSorteio": [
    "42",
    "45",
    "44",
    "60",
    "41",
    "17"
  ],
  "exibirDetalhamentoPorCidade": true,
  "id": null,
  "indicadorConcursoEspecial": 1,
  "listaDezenas": [
    "17",
    "41",
    "42",
    "44",
    "45",
    "60"
  ],
  "listaDezenasSegundoSorteio": null,
  "listaMunicipioUFGanhadores": [
    {
      "ganhadores": 1,
      "municipio": "",
      "nomeFatansiaUL": "",
      "posicao": 1,
      "serie": "",
      "uf": "SC"
    }
  ],
  "listaRateioPremio": [
    {
      "descricaoFaixa": "6 acertos",
      "faixa": 1,
      "numeroDeGanhadores": 1,
      "valorPremio": 21492982.24
    },
    {
      "descricaoFaixa": "5 acertos",
      "faixa": 2,
      "numeroDeGanhadores": 81,
      "valorPremio": 20989.74
    },
    {
      "descricaoFaixa": "4 acertos",
      "faixa": 3,
      "numeroDeGanhadores": 6642,
      "valorPremio": 255.0
    }
  ],
  "listaResultadoEquipeEsportiva": null,
  "localSorteio": "Caminhão da Sorte",
  "nomeMunicipioUFSorteio": "PALMAS, TO",
  "nomeTimeCoracaoMesSorte": "",
  "numero": 882,
  "numeroConcursoAnterior": 881,
  "numeroConcursoFinal_0_5": 885,
  "numeroConcursoProximo": 883,
  "numeroJogo": 2,
  "observacao": "",
  "premiacaoContingencia": null,
  "tipoJogo": "MEGA_SENA",
  "tipoPublicacao": 3,
  "ultimoConcurso": true,
  "valorArrecadado": 0.0,
  "valorAcumuladoConcurso_0_5": 5518234.3,
  "valorAcumuladoConcursoEspecial": 0.0,
  "valorAcumuladoProximoConcurso": 0.0,
  "valorEstimadoProximoConcurso": 1300000.0,
  "valorSaldoReservaGarantidora": 0.0,
  "valorTotalPremioFaixaUm": 0.0
}