{
  "acumulado": true,
  "dataApuracao": "12/05/2007",
  "dataProximoConcurso": "16/05/2007",
  "dezenasSorteadasOrdemSorteio": [
    "36",
    "48",
    "27",
    "40",
    "05",
    "46"
  ],
  "exibirDetalhamentoPorCidade": true,
  "id": null,
  "indicadorConcursoEspecial": 1,
  "listaDezenas": [
    "05",
    "27",
    "36",
    "40",
    "46",
    "48"
  ],
  "listaDezenasSegundoSorteio": null,
  "listaMunicipioUFGanhadores": [],
  "listaRateioPremio": [
    {
      "descricaoFaixa": "6 acertos",
      "faixa": 1,
      "numeroDeGanhadores": 0,
      "valorPremio": 0.0
    },
    {
      "descricaoFaixa": "5 acertos",
      "faixa": 2,
      "numeroDeGanhadores": 46,
      "valorPremio": 23174.32
    },
    {
      "descricaoFaixa": "4 acertos",
      "faixa": 3,
      "numeroDeGanhadores": 3704,
      "valorPremio": 286.71
    }
  ],
  "listaResultadoEquipeEsportiva": null,
  "localSorteio": "Caminhão da Sorte",
  "nomeMunicipioUFSorteio": "NATAL, RN",
  "nomeTimeCoracaoMesSorte": "",
  "numero": 866,
  "numeroConcursoAnterior": 865,
  "numeroConcursoFinal_0_5": 870,
  "numeroConcursoProximo": 867,
  "numeroJogo": 2,
  "observacao": "ACUMULOU!!! Estimativa de prêmio (6 ACERTOS) para o próximo concurso a ser realizado em 16/05/2007: R$12.000.000,00.",
  "premiacaoContingencia": null,
  "tipoJogo": "MEGA_SENA",
  "tipoPublicacao": 3,
  "ultimoConcurso": true,
  "valorArrecadado": 0.0,
  "valorAcumuladoConcurso_0_5": 2432368.47,
  "valorAcumuladoConcursoEspecial": 0.0,
  "valorAcumuladoProximoConcurso": 10212715.83,
  "valorEstimadoProximoConcurso": 0.0,
  "valorSaldoReservaGarantidora": 0.0,
  "valorTotalPremioFaixaUm": 0.0
}