{
  "acumulado": false,
  "dataApuracao": "26/03/2024",
  "dataProximoConcurso": "30/03/2024",
  "dezenasSorteadasOrdemSorteio": [
    "35",
    "02",
    "47",
    "22",
    "27",
    "16"
  ],
  "exibirDetalhamentoPorCidade": true,
  "id": null,
  "indicadorConcursoEspecial": 1,
  "listaDezenas": [
    "02",
    "16",
    "22",
    "27",
    "35",
    "47"
  ],
  "listaDezenasSegundoSorteio": null,
  "listaMunicipioUFGanhadores": [
    {
      "ganhadores": 1,
      "municipio": "RECIFE",
      "nomeFatansiaUL": "",
      "posicao": 1,
      "serie": "",
      "uf": "PE"
    }
  ],
  "listaRateioPremio": [
    {
      "descricaoFaixa": "6 acertos",
      "faixa": 1,
      "numeroDeGanhadores": 1,
      "valorPremio": 118265926.76
    },
    {
      "descricaoFaixa": "5 acertos",
      "faixa": 2,
      "numeroDeGanhadores": 182,
      "valorPremio": 32797.02
    },
    {
      "descricaoFaixa": "4 acertos",
      "faixa": 3,
      "numeroDeGanhadores": 10213,
      "valorPremio": 834.93
    }
  ],
  "listaResultadoEquipeEsportiva": null,
  "localSorteio": "ESPAÇO DA SORTE",
  "nomeMunicipioUFSorteio": "SÃO PAULO, SP",
  "nomeTimeCoracaoMesSorte": "\u0000\u0000\u0000\u0000\u0000\u0000\u0000\u0000\u0000\u0000\u0000\u0000\u0000\u0000\u0000\u0000\u0000",
  "numero": 2705,
  "numeroConcursoAnterior": 2704,
  "numeroConcursoFinal_0_5": 2710,
  "numeroConcursoProximo": 2706,
  "numeroJogo": 2,
  "observacao": "",
  "premiacaoContingencia": null,
  "tipoJogo": "MEGA_SENA",
  "tipoPublicacao": 3,
  "ultimoConcurso": true,
  "valorArrecadado": 103529715.0,
  "valorAcumuladoConcurso_0_5": 6911540.24,
  "valorAcumuladoConcursoEspecial": 37980045.39,
  "valorAcumuladoProximoConcurso": 0.0,
  "valorEstimadoProximoConcurso": 4000000.0,
  "valorSaldoReservaGarantidora": 0.0,
  "valorTotalPremioFaixaUm": 0.0
}