{
  "acumulado": true,
  "dataApuracao": "21/02/2004",
  "dataProximoConcurso": "28/02/2004",
  "dezenasSorteadasOrdemSorteio": [
    "22",
    "04",
    "30",
    "44",
    "28",
    "49"
  ],
  "exibirDetalhamentoPorCidade": true,
  "id": null,
  "indicadorConcursoEspecial": 1,
  "listaDezenas": [
    "04",
    "22",
    "28",
    "30",
    "44",
    "49"
  ],
  "listaDezenasSegundoSorteio": null,
  "listaMunicipioUFGanhadores": [],
  "listaRateioPremio": [
    {
      "descricaoFaixa": "6 acertos",
      "faixa": 1,
      "numeroDeGanhadores": 0,
      "valorPremio": 0.0
    },
    {
      "descricaoFaixa": "5 acertos",
      "faixa": 2,
      "numeroDeGanhadores": 84,
      "valorPremio": 10186.19
    },
    {
      "descricaoFaixa": "4 acertos",
      "faixa": 3,
      "numeroDeGanhadores": 4535,
      "valorPremio": 187.97
    }
  ],
  "listaResultadoEquipeEsportiva": null,
  "localSorteio": "Caminhão da Sorte",
  "nomeMunicipioUFSorteio": "EMBU, SP",
  "nomeTimeCoracaoMesSorte": "",
  "numero": 540,
  "numeroConcursoAnterior": 539,
  "numeroConcursoFinal_0_5": 545,
  "numeroConcursoProximo": 541,
  "numeroJogo": 2,
  "observacao": "ACUMULOU!!! Estimativa de prêmio (SENA) próximo concurso: R$9.000.000,00 (NOVE MILHÕES DE REAIS). A CAIXA informa que o concurso 541 da Mega Sena ocorrerá em 28/02/2004 (sábado) às 20 horas.",
  "premiacaoContingencia": null,
  "tipoJogo": "MEGA_SENA",
  "tipoPublicacao": 3,
  "ultimoConcurso": true,
  "valorArrecadado": 0.0,
  "valorAcumuladoConcurso_0_5": 1069549.88,
  "valorAcumuladoConcursoEspecial": 0.0,
  "valorAcumuladoProximoConcurso": 7225743.35,
  "valorEstimadoProximoConcurso": 0.0,
  "valorSaldoReservaGarantidora": 0.0,
  "valorTotalPremioFaixaUm": 0.0
}