{
  "acumulado": false,
  "dataApuracao": "06/11/2019",
  "dataProximoConcurso": "09/11/2019",
  "dezenasSorteadasOrdemSorteio": [
    "21",
    "42",
    "12",
    "57",
    "37",
    "28"
  ],
  "exibirDetalhamentoPorCidade": true,
  "id": null,
  "indicadorConcursoEspecial": 1,
  "listaDezenas": [
    "12",
    "21",
    "28",
    "37",
    "42",
    "57"
  ],
  "listaDezenasSegundoSorteio": null,
  "listaMunicipioUFGanhadores": [
    {
      "ganhadores": 1,
      "municipio": "SAO PAULO",
      "nomeFatansiaUL": "",
      "posicao": 1,
      "serie": "",
      "uf": "SP"
    }
  ],
  "listaRateioPremio": [
    {
      "descricaoFaixa": "6 acertos",
      "faixa": 1,
      "numeroDeGanhadores": 1,
      "valorPremio": 61429947.73
    },
    {
      "descricaoFaixa": "5 acertos",
      "faixa": 2,
      "numeroDeGanhadores": 112,
      "valorPremio": 30075.67
    },
    {
      "descricaoFaixa": "4 acertos",
      "faixa": 3,
      "numeroDeGanhadores": 6318,
      "valorPremio": 761.65
    }
  ],
  "listaResultadoEquipeEsportiva": null,
  "localSorteio": "",
  "nomeMunicipioUFSorteio": "SÃO PAULO, SP",
  "nomeTimeCoracaoMesSorte": "\u0000\u0000\u0000\u0000\u0000\u0000\u0000\u0000\u0000\u0000\u0000\u0000\u0000\u0000\u0000\u0000\u0000",
  "numero": 2205,
  "numeroConcursoAnterior": 2204,
  "numeroConcursoFinal_0_5": 2210,
  "numeroConcursoProximo": 2206,
  "numeroJogo": 2,
  "observacao": "",
  "premiacaoContingencia": null,
  "tipoJogo": "MEGA_SENA",
  "tipoPublicacao": 3,
  "ultimoConcurso": true,
  "valorArrecadado": 58424184.0,
  "valorAcumuladoConcurso_0_5": 3900340.1,
  "valorAcumuladoConcursoEspecial": 84607023.31,
  "valorAcumuladoProximoConcurso": 0.0,
  "valorEstimadoProximoConcurso": 3000000.0,
  "valorSaldoReservaGarantidora": 0.0,
  "valorTotalPremioFaixaUm": 0.0
}