{
  "acumulado": true,
  "dataApuracao": "01/06/2019",
  "dataProximoConcurso": "05/06/2019",
  "dezenasSorteadasOrdemSorteio": [
    "49",
    "39",
    "23",
    "06",
    "26",
    "01"
  ],
  "exibirDetalhamentoPorCidade": true,
  "id": null,
  "indicadorConcursoEspecial": 1,
  "listaDezenas": [
    "01",
    "06",
    "23",
    "26",
    "39",
    "49"
  ],
  "listaDezenasSegundoSorteio": null,
  "listaMunicipioUFGanhadores": [],
  "listaRateioPremio": [
    {
      "descricaoFaixa": "6 acertos",
      "faixa": 1,
      "numeroDeGanhadores": 0,
      "valorPremio": 0.0
    },
    {
      "descricaoFaixa": "5 acertos",
      "faixa": 2,
      "numeroDeGanhadores": 91,
      "valorPremio": 40927.21
    },
    {
      "descricaoFaixa": "4 acertos",
      "faixa": 3,
      "numeroDeGanhadores": 7556,
      "valorPremio": 704.14
    }
  ],
  "listaResultadoEquipeEsportiva": null,
  "localSorteio": "Caminhão da Sorte",
  "nomeMunicipioUFSorteio": "SALVADOR, BA",
  "nomeTimeCoracaoMesSorte": "",
  "numero": 2156,
  "numeroConcursoAnterior": 2155,
  "numeroConcursoFinal_0_5": 2160,
  "numeroConcursoProximo": 2157,
  "numeroJogo": 2,
  "observacao": "",
  "premiacaoContingencia": null,
  "tipoJogo": "MEGA_SENA",
  "tipoPublicacao": 3,
  "ultimoConcurso": true,
  "valorArrecadado": 64598138.5,
  "valorAcumuladoConcurso_0_5": 7957184.97,
  "valorAcumuladoConcursoEspecial": 47224673.09,
  "valorAcumuladoProximoConcurso": 54961340.62,
  "valorEstimadoProximoConcurso": 63000000.0,
  "valorSaldoReservaGarantidora": 0.0,
  "valorTotalPremioFaixaUm": 0.0
}