{
  "acumulado": true,
  "dataApuracao": "04/09/2002",
  "dataProximoConcurso": "07/09/2002",
  "dezenasSorteadasOrdemSorteio": [
    "12",
    "50",
    "36",
    "06",
    "35",
    "40"
  ],
  "exibirDetalhamentoPorCidade": true,
  "id": null,
  "indicadorConcursoEspecial": 1,
  "listaDezenas": [
    "06",
    "12",
    "35",
    "36",
    "40",
    "50"
  ],
  "listaDezenasSegundoSorteio": null,
  "listaMunicipioUFGanhadores": [],
  "listaRateioPremio": [
    {
      "descricaoFaixa": "6 acertos",
      "faixa": 1,
      "numeroDeGanhadores": 0,
      "valorPremio": 0.0
    },
    {
      "descricaoFaixa": "5 acertos",
      "faixa": 2,
      "numeroDeGanhadores": 31,
      "valorPremio": 13716.51
    },
    {
      "descricaoFaixa": "4 acertos",
      "faixa": 3,
      "numeroDeGanhadores": 1949,
      "valorPremio": 217.35
    }
  ],
  "listaResultadoEquipeEsportiva": null,
  "localSorteio": "Caminhão da Sorte",
  "nomeMunicipioUFSorteio": "Jataí, GO",
  "nomeTimeCoracaoMesSorte": "",
  "numero": 393,
  "numeroConcursoAnterior": 392,
  "numeroConcursoFinal_0_5": 395,
  "numeroConcursoProximo": 394,
  "numeroJogo": 2,
  "observacao": "Estimativa de prêmio (SENA) próximo concurso: R$1.300.000,00",
  "premiacaoContingencia": null,
  "tipoJogo": "MEGA_SENA",
  "tipoPublicacao": 3,
  "ultimoConcurso": true,
  "valorArrecadado": 0.0,
  "valorAcumuladoConcurso_0_5": 2524860.73,
  "valorAcumuladoConcursoEspecial": 0.0,
  "valorAcumuladoProximoConcurso": 510254.22,
  "valorEstimadoProximoConcurso": 0.0,
  "valorSaldoReservaGarantidora": 0.0,
  "valorTotalPremioFaixaUm": 0.0
}