{
  "acumulado": true,
  "dataApuracao": "18/08/2001",
  "dataProximoConcurso": "22/08/2001",
  "dezenasSorteadasOrdemSorteio": [
    "50",
    "09",
    "18",
    "11",
    "06",
    "17"
  ],
  "exibirDetalhamentoPorCidade": true,
  "id": null,
  "indicadorConcursoEspecial": 1,
  "listaDezenas": [
    "06",
    "09",
    "11",
    "17",
    "18",
    "50"
  ],
  "listaDezenasSegundoSorteio": null,
  "listaMunicipioUFGanhadores": [],
  "listaRateioPremio": [
    {
      "descricaoFaixa": "6 acertos",
      "faixa": 1,
      "numeroDeGanhadores": 0,
      "valorPremio": 0.0
    },
    {
      "descricaoFaixa": "5 acertos",
      "faixa": 2,
      "numeroDeGanhadores": 82,
      "valorPremio": 8749.64
    },
    {
      "descricaoFaixa": "4 acertos",
      "faixa": 3,
      "numeroDeGanhadores": 4763,
      "valorPremio": 150.07
    }
  ],
  "listaResultadoEquipeEsportiva": null,
  "localSorteio": "Caminhão da Sorte",
  "nomeMunicipioUFSorteio": "Maringá, PR",
  "nomeTimeCoracaoMesSorte": "",
  "numero": 288,
  "numeroConcursoAnterior": 287,
  "numeroConcursoFinal_0_5": 290,
  "numeroConcursoProximo": 289,
  "numeroJogo": 2,
  "observacao": "Estimativa de prêmio para o próximo concurso: (sena) R$1.500.000,00",
  "premiacaoContingencia": null,
  "tipoJogo": "MEGA_SENA",
  "tipoPublicacao": 3,
  "ultimoConcurso": true,
  "valorArrecadado": 0.0,
  "valorAcumuladoConcurso_0_5": 7108713.39,
  "valorAcumuladoConcursoEspecial": 0.0,
  "valorAcumuladoProximoConcurso": 860964.72,
  "valorEstimadoProximoConcurso": 0.0,
  "valorSaldoReservaGarantidora": 0.0,
  "valorTotalPremioFaixaUm": 0.0
}