{
  "acumulado": false,
  "dataApuracao": "09/08/2003",
  "dataProximoConcurso": "13/08/2003",
  "dezenasSorteadasOrdemSorteio": [
    "25",
    "22",
    "48",
    "52",
    "54",
    "08"
  ],
  "exibirDetalhamentoPorCidade": true,
  "id": null,
  "indicadorConcursoEspecial": 1,
  "listaDezenas": [
    "08",
    "22",
    "25",
    "48",
    "52",
    "54"
  ],
  "listaDezenasSegundoSorteio": null,
  "listaMunicipioUFGanhadores": [
    {
      "ganhadores": 2,
      "municipio": "",
      "nomeFatansiaUL": "",
      "posicao": 1,
      "serie": "",
      "uf": "SE"
    }
  ],
  "listaRateioPremio": [
    {
      "descricaoFaixa": "6 acertos",
      "faixa": 1,
      "numeroDeGanhadores": 2,
      "valorPremio": 467702.34
    },
    {
      "descricaoFaixa": "5 acertos",
      "faixa": 2,
      "numeroDeGanhadores": 104,
      "valorPremio": 7495.23
    },
    {
      "descricaoFaixa": "4 acertos",
      "faixa": 3,
      "numeroDeGanhadores": 5329,
      "valorPremio": 145.73
    }
  ],
  "listaResultadoEquipeEsportiva": null,
  "localSorteio": "Caminhão da Sorte",
  "nomeMunicipioUFSorteio": "Senhor do Bonfim, BA",
  "nomeTimeCoracaoMesSorte": "",
  "numero": 487,
  "numeroConcursoAnterior": 486,
  "numeroConcursoFinal_0_5": 490,
  "numeroConcursoProximo": 488,
  "numeroJogo": 2,
  "observacao": "Estimativa de prêmio (SENA) próximo concurso: R$750.000,00.",
  "premiacaoContingencia": null,
  "tipoJogo": "MEGA_SENA",
  "tipoPublicacao": 3,
  "ultimoConcurso": true,
  "valorArrecadado": 0.0,
  "valorAcumuladoConcurso_0_5": 6908624.25,
  "valorAcumuladoConcursoEspecial": 0.0,
  "valorAcumuladoProximoConcurso": 0.0,
  "valorEstimadoProximoConcurso": 0.0,
  "valorSaldoReservaGarantidora": 0.0,
  "valorTotalPremioFaixaUm": 0.0
}