{
  "acumulado": true,
  "dataApuracao": "16/11/2022",
  "dataProximoConcurso": "19/11/2022",
  "dezenasSorteadasOrdemSorteio": [
    "59",
    "36",
    "23",
    "01",
    "33",
    "32"
  ],
  "exibirDetalhamentoPorCidade": true,
  "id": null,
  "indicadorConcursoEspecial": 1,
  "listaDezenas": [
    "01",
    "23",
    "32",
    "33",
    "36",
    "59"
  ],
  "listaDezenasSegundoSorteio": null,
  "listaMunicipioUFGanhadores": [],
  "listaRateioPremio": [
    {
      "descricaoFaixa": "6 acertos",
      "faixa": 1,
      "numeroDeGanhadores": 0,
      "valorPremio": 0.0
    },
    {
      "descricaoFaixa": "5 acertos",
      "faixa": 2,
      "numeroDeGanhadores": 32,
      "valorPremio": 75686.31
    },
    {
      "descricaoFaixa": "4 acertos",
      "faixa": 3,
      "numeroDeGanhadores": 3223,
      "valorPremio": 1073.51
    }
  ],
  "listaResultadoEquipeEsportiva": null,
  "localSorteio": "ESPAÇO DA SORTE",
  "nomeMunicipioUFSorteio": "SÃO PAULO,  SP",
  "nomeTimeCoracaoMesSorte": "\u0000\u0000\u0000\u0000\u0000\u0000\u0000\u0000\u0000\u0000\u0000\u0000\u0000\u0000\u0000\u0000\u0000",
  "numero": 2539,
  "numeroConcursoAnterior": 2538,
  "numeroConcursoFinal_0_5": 2540,
  "numeroConcursoProximo": 2540,
  "numeroJogo": 2,
  "observacao": "",
  "premiacaoContingencia": null,
  "tipoJogo": "MEGA_SENA",
  "tipoPublicacao": 3,
  "ultimoConcurso": true,
  "valorArrecadado": 42007473.0,
  "valorAcumuladoConcurso_0_5": 31145754.74,
  "valorAcumuladoConcursoEspecial": 123703571.12,
  "valorAcumuladoProximoConcurso": 31145754.74,
  "valorEstimadoProximoConcurso": 38000000.0,
  "valorSaldoReservaGarantidora": 0.0,
  "valorTotalPremioFaixaUm": 0.0
}