{
  "acumulado": true,
  "dataApuracao": "08/11/2008",
  "dataProximoConcurso": "12/11/2008",
  "dezenasSorteadasOrdemSorteio": [
    "19",
    "32",
    "52",
    "01",
    "02",
    "39"
  ],
  "exibirDetalhamentoPorCidade": true,
  "id": null,
  "indicadorConcursoEspecial": 1,
  "listaDezenas": [
    "01",
    "02",
    "19",
    "32",
    "39",
    "52"
  ],
  "listaDezenasSegundoSorteio": null,
  "listaMunicipioUFGanhadores": [],
  "listaRateioPremio": [
    {
      "descricaoFaixa": "6 acertos",
      "faixa": 1,
      "numeroDeGanhadores": 0,
      "valorPremio": 0.0
    },
    {
      "descricaoFaixa": "5 acertos",
      "faixa": 2,
      "numeroDeGanhadores": 56,
      "valorPremio": 27920.81
    },
    {
      "descricaoFaixa": "4 acertos",
      "faixa": 3,
      "numeroDeGanhadores": 4646,
      "valorPremio": 336.54
    }
  ],
  "listaResultadoEquipeEsportiva": null,
  "localSorteio": "Caminhão da Sorte",
  "nomeMunicipioUFSorteio": "SÃO JOSÉ DO RIO PRETO, SP",
  "nomeTimeCoracaoMesSorte": "",
  "numero": 1020,
  "numeroConcursoAnterior": 1019,
  "numeroConcursoFinal_0_5": 1025,
  "numeroConcursoProximo": 1021,
  "numeroJogo": 2,
  "observacao": "",
  "premiacaoContingencia": null,
  "tipoJogo": "MEGA_SENA",
  "tipoPublicacao": 3,
  "ultimoConcurso": true,
  "valorArrecadado": 0.0,
  "valorAcumuladoConcurso_0_5": 1810444.47,
  "valorAcumuladoConcursoEspecial": 9484749.33,
  "valorAcumuladoProximoConcurso": 14716218.54,
  "valorEstimadoProximoConcurso": 18000000.0,
  "valorSaldoReservaGarantidora": 0.0,
  "valorTotalPremioFaixaUm": 0.0
}