{
  "acumulado": true,
  "dataApuracao": "13/07/2002",
  "dataProximoConcurso": "17/07/2002",
  "dezenasSorteadasOrdemSorteio": [
    "55",
    "45",
    "48",
    "41",
    "05",
    "38"
  ],
  "exibirDetalhamentoPorCidade": true,
  "id": null,
  "indicadorConcursoEspecial": 1,
  "listaDezenas": [
    "05",
    "38",
    "41",
    "45",
    "48",
    "55"
  ],
  "listaDezenasSegundoSorteio": null,
  "listaMunicipioUFGanhadores": [],
  "listaRateioPremio": [
    {
      "descricaoFaixa": "6 acertos",
      "faixa": 1,
      "numeroDeGanhadores": 0,
      "valorPremio": 0.0
    },
    {
      "descricaoFaixa": "5 acertos",
      "faixa": 2,
      "numeroDeGanhadores": 36,
      "valorPremio": 25450.6
    },
    {
      "descricaoFaixa": "4 acertos",
      "faixa": 3,
      "numeroDeGanhadores": 3115,
      "valorPremio": 293.02
    }
  ],
  "listaResultadoEquipeEsportiva": null,
  "localSorteio": "Caminhão da Sorte",
  "nomeMunicipioUFSorteio": "Jaboticabal, SP",
  "nomeTimeCoracaoMesSorte": "",
  "numero": 378,
  "numeroConcursoAnterior": 377,
  "numeroConcursoFinal_0_5": 380,
  "numeroConcursoProximo": 379,
  "numeroJogo": 2,
  "observacao": "Estimativa de prêmio (SENA) próximo concurso: R$5.400.000,00.",
  "premiacaoContingencia": null,
  "tipoJogo": "MEGA_SENA",
  "tipoPublicacao": 3,
  "ultimoConcurso": true,
  "valorArrecadado": 0.0,
  "valorAcumuladoConcurso_0_5": 5247170.3,
  "valorAcumuladoConcursoEspecial": 0.0,
  "valorAcumuladoProximoConcurso": 4498508.08,
  "valorEstimadoProximoConcurso": 0.0,
  "valorSaldoReservaGarantidora": 0.0,
  "valorTotalPremioFaixaUm": 0.0
}