{
  "acumulado": true,
  "dataApuracao": "09/01/1999",
  "dataProximoConcurso": "",
  "dezenasSorteadasOrdemSorteio": [
    "11",
    "45",
    "48",
    "07",
    "28",
    "20"
  ],
  "exibirDetalhamentoPorCidade": true,
  "id": null,
  "indicadorConcursoEspecial": 1,
  "listaDezenas": [
    "07",
    "11",
    "20",
    "28",
    "45",
    "48"
  ],
  "listaDezenasSegundoSorteio": null,
  "listaMunicipioUFGanhadores": [],
  "listaRateioPremio": [
    {
      "descricaoFaixa": "6 acertos",
      "faixa": 1,
      "numeroDeGanhadores": 0,
      "valorPremio": 0.0
    },
    {
      "descricaoFaixa": "5 acertos",
      "faixa": 2,
      "numeroDeGanhadores": 106,
      "valorPremio": 9795.13
    },
    {
      "descricaoFaixa": "4 acertos",
      "faixa": 3,
      "numeroDeGanhadores": 6290,
      "valorPremio": 164.74
    }
  ],
  "listaResultadoEquipeEsportiva": null,
  "localSorteio": "Auditório",
  "nomeMunicipioUFSorteio": "Brasília, DF",
  "nomeTimeCoracaoMesSorte": "",
  "numero": 149,
  "numeroConcursoAnterior": 148,
  "numeroConcursoFinal_0_5": 150,
  "numeroConcursoProximo": 150,
  "numeroJogo": 2,
  "observacao": "A MEGA ACUMULOU - O prêmio do CONC.150 pode chegar a 21,2 Milhões.",
  "premiacaoContingencia": null,
  "tipoJogo": "MEGA_SENA",
  "tipoPublicacao": 3,
  "ultimoConcurso": true,
  "valorArrecadado": 0.0,
  "valorAcumuladoConcurso_0_5": 16758059.96,
  "valorAcumuladoConcursoEspecial": 0.0,
  "valorAcumuladoProximoConcurso": 2211820.94,
  "valorEstimadoProximoConcurso": 0.0,
  "valorSaldoReservaGarantidora": 0.0,
  "valorTotalPremioFaixaUm": 0.0
}