{
  "acumulado": false,
  "dataApuracao": "23/05/2007",
  "dataProximoConcurso": "26/05/2007",
  "dezenasSorteadasOrdemSorteio": [
    "29",
    "42",
    "50",
    "51",
    "49",
    "27"
  ],
  "exibirDetalhamentoPorCidade": true,
  "id": null,
  "indicadorConcursoEspecial": 1,
  "listaDezenas": [
    "27",
    "29",
    "42",
    "49",
    "50",
    "51"
  ],
  "listaDezenasSegundoSorteio": null,
  "listaMunicipioUFGanhadores": [
    {
      "ganhadores": 1,
      "municipio": "",
      "nomeFatansiaUL": "",
      "posicao": 1,
      "serie": "",
      "uf": "SP"
    }
  ],
  "listaRateioPremio": [
    {
      "descricaoFaixa": "6 acertos",
      "faixa": 1,
      "numeroDeGanhadores": 1,
      "valorPremio": 16192436.64
    },
    {
      "descricaoFaixa": "5 acertos",
      "faixa": 2,
      "numeroDeGanhadores": 57,
      "valorPremio": 20414.39
    },
    {
      "descricaoFaixa": "4 acertos",
      "faixa": 3,
      "numeroDeGanhadores": 3912,
      "valorPremio": 296.32
    }
  ],
  "listaResultadoEquipeEsportiva": null,
  "localSorteio": "Caminhão da Sorte",
  "nomeMunicipioUFSorteio": "IPORÁ, GO",
  "nomeTimeCoracaoMesSorte": "",
  "numero": 869,
  "numeroConcursoAnterior": 868,
  "numeroConcursoFinal_0_5": 870,
  "numeroConcursoProximo": 870,
  "numeroJogo": 2,
  "observacao": "",
  "premiacaoContingencia": null,
  "tipoJogo": "MEGA_SENA",
  "tipoPublicacao": 3,
  "ultimoConcurso": true,
  "valorArrecadado": 0.0,
  "valorAcumuladoConcurso_0_5": 6703597.67,
  "valorAcumuladoConcursoEspecial": 0.0,
  "valorAcumuladoProximoConcurso": 0.0,
  "valorEstimadoProximoConcurso": 9000000.0,
  "valorSaldoReservaGarantidora": 0.0,
  "valorTotalPremioFaixaUm": 0.0
}